{
  "sections": {
    "ds_hero": {
      "type": "ds-hero",
      "settings": {
        "title": "WHERE AMBITION COMPETES",
        "description": "APAC'S PREMIER MULTI-TITLE ESPORTS ORGANIZATION. ELITE PERFORMANCE. UNYIELDING CREATION."
      }
    },
    "ds_ticker": {
      "type": "ds-ticker",
      "settings": {}
    },
    "ds_roster_preview": {
      "type": "ds-roster-preview",
      "settings": {}
    },
    "ds_results_preview": {
      "type": "ds-results-preview",
      "settings": {}
    },
    "ds_content_proof": {
      "type": "ds-content-proof",
      "settings": {}
    },
    "ds_sponsor_signal": {
      "type": "ds-sponsor-signal",
      "settings": {}
    },
    "ds_merch_entry": {
      "type": "ds-merch-entry",
      "settings": {}
    }
  },
  "order": [
    "ds_hero",
    "ds_ticker",
    "ds_roster_preview",
    "ds_results_preview",
    "ds_content_proof",
    "ds_sponsor_signal",
    "ds_merch_entry"
  ]
}
